key_drivers-0.1.6.dist-info/METADATA
key_drivers-0.1.6.dist-info/WHEEL
key_drivers-0.1.6.dist-info/licenses/LICENSE
key_drivers/__init__.py
key_drivers/auto_insight.py
key_drivers/metric_decomposition.py
key_drivers-0.1.6.dist-info/RECORD
