Metadata-Version: 2.1
Name: key-drivers
Version: 0.1.6
Summary: A little helper to help automatically find key drivers of KPIs through time.
Author-Email: Oracen <alex.stenlake@gmail.com>
License: MIT
Requires-Python: <3.12,>=3.10
Requires-Dist: scikit-learn>=1.5.1
Requires-Dist: umap-learn>=0.5.6
Requires-Dist: pandas>=2.2.2
